README
setup.py
transdb/__init__.py
transdb/fields.py
transdb/widgets.py
transdb/xml_serializer.py
transdb.egg-info/PKG-INFO
transdb.egg-info/SOURCES.txt
transdb.egg-info/dependency_links.txt
transdb.egg-info/top_level.txt