Metadata-Version: 1.0
Name: transdb
Version: 0.9
Summary: I18n django reusable app 
Home-page: http://code.google.com/p/transdb/
Author: garcia.marc
Author-email: di@sferos.com
License: UNKNOWN
Keywords: django,translation,internationalization,i18n,database,model
Platform: UNKNOWN
Classifier: Programming Language :: Python
Classifier: Topic :: Software Development :: Internationalization
Classifier: Framework :: Django
